{
	"projectid": "1110362897_DEGINX",
	"setting": {
		"urlCheck": false,
		"es6": true,
		"postcss": false,
		"minified": true,
		"newFeature": true,
		"autoAudits": true,
		"nodeModules": true,
		"uploadWithSourceMap": true,
		"uglifyFileName": true,
		"remoteDebugLogEnable": false
	},
	"qqLibVersion": "1.14.0",
	"compileType": "miniprogram",
	"createTime": 1587473250587,
	"accessTime": 1587473250587,
	"packOptions": {
		"ignore": []
	},
	"debugOptions": {
		"hidedInDevtools": []
	},
	"qqappid": "1110362897",
	"projectname": "DEGINX",
	"scripts": {},
	"condition": {
		"search": {
			"current": -1,
			"list": []
		},
		"conversation": {
			"current": -1,
			"list": []
		},
		"game": {
			"currentL": -1,
			"list": []
		},
		"miniprogram": {
			"current": -1,
			"list": []
		}
	}
}